metax_api/__init__.py
metax_api/__main__.py
metax_api/api.py
metax_api/errors.py
metax_api/request.py
metax_api/types.py
metax_api/db/__init__.py
metax_api/db/__main__.py
metax_api/db/copy.py
metax_api/db/delete.py
metax_api/db/friends.py
metax_api/db/get.py
metax_api/db/keys.py
metax_api/db/listener.py
metax_api/db/metax_base.py
metax_api/db/metax_info.py
metax_api/db/pair.py
metax_api/db/peers.py
metax_api/db/save.py
metax_api/db/send_to.py
metax_api/db/share.py
metax_api/db/update.py
metax_api-0.3.dist-info/METADATA
metax_api-0.3.dist-info/WHEEL
metax_api-0.3.dist-info/top_level.txt
metax_api-0.3.dist-info/RECORD
