Metadata-Version: 2.1
Name: metax_api
Version: 0.3
Summary: Pyhton3 api client for metax
Author-email: Mikhayil Martirosyan <mikhayil.martirosyan@realschool.am>
Project-URL: Homepage, https://gitlab.com/mm_arm/metax.api
Project-URL: Bug Tracker, https://gitlab.com/mm_arm/metax.api/issues
Keywords: Metax,Leviathan,Ehayq,EhayqLLC,Instigate,Metax.api
Classifier: Programming Language :: Python :: 3
Classifier: License :: OSI Approved :: MIT License
Classifier: Operating System :: OS Independent
Requires-Python: >=3.7
